{
  "_class": "shapeGroup",
  "booleanOperation": -1,
  "clippingMaskMode": 0,
  "do_objectID": "D06CC7DC-9CCA-469A-9F65-077AD34BF0B0",
  "exportOptions": {
    "_class": "exportOptions",
    "do_objectID": "E82774C0-F90F-48EF-B7E2-3B96EA4595AB",
    "exportFormats": [
    ],
    "includedLayerIds": [
    ],
    "layerOptions": 0,
    "shouldTrim": false
  },
  "frame": {
    "_class": "rect",
    "constrainProportions": false,
    "do_objectID": "261A5A3E-C1A9-4207-9D41-462B83767962",
    "height": 18.00030000000004,
    "width": 18.00050000000002,
    "x": 2.999750000000005,
    "y": 2.999699999999962
  },
  "groupLayout": {
    "_class": "MSImmutableFreeformGroupLayout"
  },
  "hasClickThrough": false,
  "hasClippingMask": true,
  "isFixedToViewport": false,
  "isFlippedHorizontal": false,
  "isFlippedVertical": false,
  "isLocked": false,
  "isVisible": true,
  "layerListExpandedType": 0,
  "layers": [
    {
      "class": "shapePath",
      "id": "D763BB89-E82C-4C2F-AF6C-ADA4C11C157A"
    },
    {
      "class": "shapePath",
      "id": "9FCDDB29-C116-4559-98F3-4511816D5511"
    },
    {
      "class": "shapePath",
      "id": "81BE29AD-5896-4164-B34C-A44C1EB56C9B"
    }
  ],
  "name": "color",
  "nameIsFixed": false,
  "resizingConstraint": 63,
  "resizingType": 0,
  "rotation": 0,
  "sharedStyleID": "B0E9C828-014A-447D-AB3D-6EA556512153",
  "shouldBreakMaskChain": false,
  "style": {
    "_class": "style",
    "borders": [
      {
        "_class": "border",
        "color": {
          "_class": "color",
          "alpha": 1,
          "blue": 0.592,
          "green": 0.592,
          "red": 0.592
        },
        "fillType": 0,
        "isEnabled": false,
        "position": 1,
        "thickness": 1
      }
    ],
    "do_objectID": "6D06A16F-29BD-4660-9415-E859B7A1C882",
    "endMarkerType": 0,
    "fills": [
      {
        "_class": "fill",
        "color": {
          "_class": "color",
          "alpha": 1,
          "blue": 0.1882352941176471,
          "green": 0.1568627450980392,
          "red": 0.1490196078431373
        },
        "fillType": 0,
        "isEnabled": true,
        "noiseIndex": 0,
        "noiseIntensity": 0,
        "patternFillType": 1,
        "patternTileScale": 1
      }
    ],
    "miterLimit": 10,
    "startMarkerType": 0,
    "windingRule": 1
  },
  "windingRule": 1
}