{
  "_class": "shapeGroup",
  "booleanOperation": -1,
  "clippingMaskMode": 0,
  "do_objectID": "C2C742BB-BE07-4D93-987C-4DF9F2506A32",
  "exportOptions": {
    "_class": "exportOptions",
    "exportFormats": [
    ],
    "includedLayerIds": [
    ],
    "layerOptions": 0,
    "shouldTrim": false
  },
  "frame": {
    "_class": "rect",
    "constrainProportions": false,
    "height": 16,
    "width": 20.00022203440101,
    "x": 2,
    "y": 4
  },
  "groupLayout": {
    "_class": "MSImmutableFreeformGroupLayout"
  },
  "hasClickThrough": false,
  "hasClippingMask": true,
  "isFixedToViewport": false,
  "isFlippedHorizontal": false,
  "isFlippedVertical": false,
  "isLocked": false,
  "isVisible": true,
  "layerListExpandedType": 1,
  "layers": [
    {
      "class": "shapePath",
      "id": "81F99CFC-E546-4FAA-A473-82F5C5CF3CC7"
    },
    {
      "class": "shapePath",
      "id": "8EF0F1C6-380C-4882-B754-E45E99A75B73"
    },
    {
      "class": "shapePath",
      "id": "755C1FDA-9E8E-481F-BBA2-7DECA79009A9"
    },
    {
      "class": "shapePath",
      "id": "F7EEEB4B-CEBF-4532-B6BB-45B513ECF003"
    }
  ],
  "name": "color",
  "nameIsFixed": false,
  "resizingConstraint": 63,
  "resizingType": 0,
  "rotation": 0,
  "sharedStyleID": "B0E9C828-014A-447D-AB3D-6EA556512153",
  "shouldBreakMaskChain": false,
  "style": {
    "_class": "style",
    "borders": [
      {
        "_class": "border",
        "color": {
          "_class": "color",
          "alpha": 1,
          "blue": 0.592,
          "green": 0.592,
          "red": 0.592
        },
        "fillType": 0,
        "isEnabled": false,
        "position": 1,
        "thickness": 1
      }
    ],
    "do_objectID": "89BA9368-BB7B-42AD-81BF-E635547BF1E5",
    "endMarkerType": 0,
    "fills": [
      {
        "_class": "fill",
        "color": {
          "_class": "color",
          "alpha": 1,
          "blue": 0.1882352941176471,
          "green": 0.1568627450980392,
          "red": 0.1490196078431373
        },
        "fillType": 0,
        "isEnabled": true,
        "noiseIndex": 0,
        "noiseIntensity": 0,
        "patternFillType": 1,
        "patternTileScale": 1
      }
    ],
    "miterLimit": 10,
    "startMarkerType": 0,
    "windingRule": 1
  },
  "windingRule": 1
}