{
  "_class": "symbolMaster",
  "allowsOverrides": true,
  "backgroundColor": {
    "_class": "color",
    "alpha": 1,
    "blue": 1,
    "do_objectID": "C1409D80-7254-44D7-A1FC-C3BAB6FEEBDE",
    "green": 1,
    "red": 1
  },
  "booleanOperation": 0,
  "changeIdentifier": 674,
  "clippingMaskMode": 0,
  "do_objectID": "511EE4A5-D9DE-4930-AF38-814F88374AEF",
  "exportOptions": {
    "_class": "exportOptions",
    "do_objectID": "B53E4A9B-2F4D-4277-A4DF-DA420B793DB4",
    "exportFormats": [
      {
        "_class": "exportFormat",
        "absoluteSize": 0,
        "fileFormat": "svg",
        "name": "",
        "namingScheme": 0,
        "scale": 1,
        "visibleScaleType": 0
      }
    ],
    "includedLayerIds": [
    ],
    "layerOptions": 0,
    "shouldTrim": false
  },
  "frame": {
    "_class": "rect",
    "constrainProportions": false,
    "do_objectID": "8D505335-585C-4EE3-A1F8-A87140350D31",
    "height": 24,
    "width": 24,
    "x": 763,
    "y": 274
  },
  "groupLayout": {
    "_class": "MSImmutableFreeformGroupLayout"
  },
  "hasBackgroundColor": false,
  "hasClickThrough": true,
  "hasClippingMask": false,
  "horizontalRulerData": {
    "_class": "rulerData",
    "base": 0,
    "do_objectID": "6560446F-A273-4446-91C6-DAF51BFE582E",
    "guides": [
    ]
  },
  "includeBackgroundColorInExport": true,
  "includeBackgroundColorInInstance": false,
  "includeInCloudUpload": true,
  "isFixedToViewport": false,
  "isFlippedHorizontal": false,
  "isFlippedVertical": false,
  "isFlowHome": false,
  "isLocked": false,
  "isVisible": true,
  "layerListExpandedType": 2,
  "layers": [
    {
      "class": "shapeGroup",
      "id": "D5B83C32-C039-4015-8ED2-C48C5CE03A2B"
    }
  ],
  "name": "eye",
  "nameIsFixed": true,
  "overrideProperties": [
    {
      "_class": "MSImmutableOverrideProperty",
      "canOverride": true,
      "overrideName": "D5B83C32-C039-4015-8ED2-C48C5CE03A2B_layerStyle"
    }
  ],
  "resizesContent": false,
  "resizingConstraint": 63,
  "resizingType": 0,
  "rotation": 0,
  "shouldBreakMaskChain": true,
  "style": {
    "_class": "style",
    "do_objectID": "F04C8836-9C07-4084-93E8-49B16924B90D",
    "endMarkerType": 0,
    "miterLimit": 10,
    "startMarkerType": 0,
    "windingRule": 1
  },
  "symbolID": "A696770F-52E4-48C0-AF48-C0873D8DC7B0",
  "verticalRulerData": {
    "_class": "rulerData",
    "base": 0,
    "do_objectID": "DAC5875B-3BF2-46D2-9D1C-350AB56A3FED",
    "guides": [
    ]
  }
}