{
  "_class": "symbolMaster",
  "allowsOverrides": true,
  "backgroundColor": {
    "_class": "color",
    "alpha": 1,
    "blue": 1,
    "do_objectID": "571C6319-8F9F-4340-A8D1-0518CA2404DB",
    "green": 1,
    "red": 1
  },
  "booleanOperation": -1,
  "changeIdentifier": 129,
  "clippingMaskMode": 0,
  "do_objectID": "7C6655E7-F9AD-4A3C-8C8B-8AC3EDA82F0C",
  "exportOptions": {
    "_class": "exportOptions",
    "do_objectID": "2369EB7E-9FF2-4038-B4C0-7D6671BCC40A",
    "exportFormats": [
      {
        "_class": "exportFormat",
        "absoluteSize": 0,
        "fileFormat": "svg",
        "name": "",
        "namingScheme": 0,
        "scale": 1,
        "visibleScaleType": 0
      }
    ],
    "includedLayerIds": [
    ],
    "layerOptions": 0,
    "shouldTrim": false
  },
  "frame": {
    "_class": "rect",
    "constrainProportions": false,
    "do_objectID": "BBC082B8-411E-491D-AFCF-7E0EC6A5680C",
    "height": 24,
    "width": 24,
    "x": 139,
    "y": 178
  },
  "groupLayout": {
    "_class": "MSImmutableFreeformGroupLayout"
  },
  "hasBackgroundColor": false,
  "hasClickThrough": true,
  "hasClippingMask": false,
  "horizontalRulerData": {
    "_class": "rulerData",
    "base": 0,
    "do_objectID": "A266E3FA-CDEE-4050-A427-8AD2DEB24310",
    "guides": [
    ]
  },
  "includeBackgroundColorInExport": true,
  "includeBackgroundColorInInstance": true,
  "includeInCloudUpload": true,
  "isFixedToViewport": false,
  "isFlippedHorizontal": false,
  "isFlippedVertical": false,
  "isFlowHome": false,
  "isLocked": false,
  "isVisible": true,
  "layerListExpandedType": 2,
  "layers": [
    {
      "class": "shapeGroup",
      "id": "CBE1CD4B-E62C-4B0E-98E2-AED3E0B070A0"
    }
  ],
  "name": "bluetooth",
  "nameIsFixed": true,
  "overrideProperties": [
    {
      "_class": "MSImmutableOverrideProperty",
      "canOverride": true,
      "overrideName": "CBE1CD4B-E62C-4B0E-98E2-AED3E0B070A0_layerStyle"
    }
  ],
  "resizesContent": false,
  "resizingConstraint": 63,
  "resizingType": 0,
  "rotation": 0,
  "shouldBreakMaskChain": true,
  "style": {
    "_class": "style",
    "do_objectID": "F23CDBD3-B686-4B33-AF91-4E2C4E67AFBE",
    "endMarkerType": 0,
    "miterLimit": 10,
    "startMarkerType": 0,
    "windingRule": 1
  },
  "symbolID": "3AD42898-9E2E-4096-B96D-80534F9A06BD",
  "verticalRulerData": {
    "_class": "rulerData",
    "base": 0,
    "do_objectID": "5443B171-D89D-43C2-92D5-C7044E2FD31D",
    "guides": [
    ]
  }
}