{
  "_class": "shapePath",
  "booleanOperation": -1,
  "clippingMaskMode": 0,
  "do_objectID": "731D88DE-AB27-4C9E-AB7D-B4159027E509",
  "edited": true,
  "exportOptions": {
    "_class": "exportOptions",
    "do_objectID": "4C21629D-EFE5-4762-A096-A2F26B563D12",
    "exportFormats": [
    ],
    "includedLayerIds": [
    ],
    "layerOptions": 0,
    "shouldTrim": false
  },
  "frame": {
    "_class": "rect",
    "constrainProportions": false,
    "do_objectID": "D23BD722-8B86-4AA5-8289-ABB55A67F139",
    "height": 18,
    "width": 20,
    "x": 0,
    "y": 0
  },
  "hasClippingMask": false,
  "isClosed": true,
  "isFixedToViewport": false,
  "isFlippedHorizontal": false,
  "isFlippedVertical": false,
  "isLocked": false,
  "isVisible": true,
  "layerListExpandedType": 0,
  "name": "Path",
  "nameIsFixed": false,
  "pointRadiusBehaviour": 1,
  "points": [
    {
      "_class": "curvePoint",
      "cornerRadius": 0,
      "curveFrom": "{0.98124999999999996, 0.4566111111111108}",
      "curveMode": 1,
      "curveTo": "{0.98124999999999996, 0.4566111111111108}",
      "hasCurveFrom": false,
      "hasCurveTo": false,
      "point": "{0.98124999999999996, 0.4566111111111108}"
    },
    {
      "_class": "curvePoint",
      "cornerRadius": 0,
      "curveFrom": "{0.75, 0.25105555555555586}",
      "curveMode": 1,
      "curveTo": "{0.75, 0.25105555555555586}",
      "hasCurveFrom": false,
      "hasCurveTo": false,
      "point": "{0.75, 0.25105555555555586}"
    },
    {
      "_class": "curvePoint",
      "cornerRadius": 0,
      "curveFrom": "{0.75, 0.049833333333332855}",
      "curveMode": 4,
      "curveTo": "{0.75, 0.1111111111111111}",
      "hasCurveFrom": true,
      "hasCurveTo": false,
      "point": "{0.75, 0.1111111111111111}"
    },
    {
      "_class": "curvePoint",
      "cornerRadius": 0,
      "curveFrom": "{0.65935000000000055, 0}",
      "curveMode": 4,
      "curveTo": "{0.70935000000000059, 0}",
      "hasCurveFrom": false,
      "hasCurveTo": true,
      "point": "{0.65935000000000055, 0}"
    },
    {
      "_class": "curvePoint",
      "cornerRadius": 0,
      "curveFrom": "{0.040649999999999409, 0}",
      "curveMode": 4,
      "curveTo": "{0.090600000000000597, 0}",
      "hasCurveFrom": true,
      "hasCurveTo": false,
      "point": "{0.090600000000000597, 0}"
    },
    {
      "_class": "curvePoint",
      "cornerRadius": 0,
      "curveFrom": "{0, 0.1111111111111111}",
      "curveMode": 4,
      "curveTo": "{0, 0.049833333333332855}",
      "hasCurveFrom": false,
      "hasCurveTo": true,
      "point": "{0, 0.1111111111111111}"
    },
    {
      "_class": "curvePoint",
      "cornerRadius": 0,
      "curveFrom": "{0, 0.71516666666666617}",
      "curveMode": 4,
      "curveTo": "{0, 0.66666666666666663}",
      "hasCurveFrom": true,
      "hasCurveTo": false,
      "point": "{0, 0.66666666666666663}"
    },
    {
      "_class": "curvePoint",
      "cornerRadius": 0,
      "curveFrom": "{0.054050000000000861, 0.79044444444444495}",
      "curveMode": 4,
      "curveTo": "{0.025650000000001682, 0.75605555555555604}",
      "hasCurveFrom": true,
      "hasCurveTo": true,
      "point": "{0.061050000000000181, 0.77122222222222248}"
    },
    {
      "_class": "curvePoint",
      "cornerRadius": 0,
      "curveFrom": "{0.050000000000000003, 0.92522222222222206}",
      "curveMode": 3,
      "curveTo": "{0.050000000000000003, 0.81133333333333413}",
      "hasCurveFrom": true,
      "hasCurveTo": true,
      "point": "{0.050000000000000003, 0.83333333333333337}"
    },
    {
      "_class": "curvePoint",
      "cornerRadius": 0,
      "curveFrom": "{0.28269999999999984, 1}",
      "curveMode": 2,
      "curveTo": "{0.11730000000000018, 1}",
      "hasCurveFrom": true,
      "hasCurveTo": true,
      "point": "{0.20000000000000001, 1}"
    },
    {
      "_class": "curvePoint",
      "cornerRadius": 0,
      "curveFrom": "{0.34999999999999998, 0.81372222222222179}",
      "curveMode": 3,
      "curveTo": "{0.34999999999999998, 0.92522222222222206}",
      "hasCurveFrom": true,
      "hasCurveTo": true,
      "point": "{0.34999999999999998, 0.83333333333333337}"
    },
    {
      "_class": "curvePoint",
      "cornerRadius": 0,
      "curveFrom": "{0.34075000000000272, 0.77777777777777779}",
      "curveMode": 4,
      "curveTo": "{0.34639999999999987, 0.79522222222222183}",
      "hasCurveFrom": false,
      "hasCurveTo": true,
      "point": "{0.34075000000000272, 0.77777777777777779}"
    },
    {
      "_class": "curvePoint",
      "cornerRadius": 0,
      "curveFrom": "{0.5, 0.77777777777777779}",
      "curveMode": 1,
      "curveTo": "{0.5, 0.77777777777777779}",
      "hasCurveFrom": false,
      "hasCurveTo": false,
      "point": "{0.5, 0.77777777777777779}"
    },
    {
      "_class": "curvePoint",
      "cornerRadius": 0,
      "curveFrom": "{0.65360000000000018, 0.79522222222222183}",
      "curveMode": 4,
      "curveTo": "{0.65924999999999723, 0.77777777777777779}",
      "hasCurveFrom": true,
      "hasCurveTo": false,
      "point": "{0.65924999999999723, 0.77777777777777779}"
    },
    {
      "_class": "curvePoint",
      "cornerRadius": 0,
      "curveFrom": "{0.65000000000000002, 0.92522222222222206}",
      "curveMode": 3,
      "curveTo": "{0.65000000000000002, 0.81372222222222179}",
      "hasCurveFrom": true,
      "hasCurveTo": true,
      "point": "{0.65000000000000002, 0.83333333333333337}"
    },
    {
      "_class": "curvePoint",
      "cornerRadius": 0,
      "curveFrom": "{0.88269999999999982, 1}",
      "curveMode": 2,
      "curveTo": "{0.71730000000000016, 1}",
      "hasCurveFrom": true,
      "hasCurveTo": true,
      "point": "{0.80000000000000004, 1}"
    },
    {
      "_class": "curvePoint",
      "cornerRadius": 0,
      "curveFrom": "{0.94999999999999996, 0.81372222222222179}",
      "curveMode": 3,
      "curveTo": "{0.94999999999999996, 0.92522222222222206}",
      "hasCurveFrom": true,
      "hasCurveTo": true,
      "point": "{0.94999999999999996, 0.83333333333333337}"
    },
    {
      "_class": "curvePoint",
      "cornerRadius": 0,
      "curveFrom": "{0.94075000000000275, 0.77777777777777779}",
      "curveMode": 4,
      "curveTo": "{0.94639999999999991, 0.79522222222222183}",
      "hasCurveFrom": false,
      "hasCurveTo": true,
      "point": "{0.94075000000000275, 0.77777777777777779}"
    },
    {
      "_class": "curvePoint",
      "cornerRadius": 0,
      "curveFrom": "{0.97764999999999991, 0.77777777777777779}",
      "curveMode": 4,
      "curveTo": "{0.94999999999999996, 0.77777777777777779}",
      "hasCurveFrom": true,
      "hasCurveTo": false,
      "point": "{0.94999999999999996, 0.77777777777777779}"
    },
    {
      "_class": "curvePoint",
      "cornerRadius": 0,
      "curveFrom": "{1, 0.72222222222222221}",
      "curveMode": 4,
      "curveTo": "{1, 0.75294444444444431}",
      "hasCurveFrom": false,
      "hasCurveTo": true,
      "point": "{1, 0.72222222222222221}"
    },
    {
      "_class": "curvePoint",
      "cornerRadius": 0,
      "curveFrom": "{1, 0.48311111111111099}",
      "curveMode": 4,
      "curveTo": "{1, 0.5}",
      "hasCurveFrom": true,
      "hasCurveTo": false,
      "point": "{1, 0.5}"
    },
    {
      "_class": "curvePoint",
      "cornerRadius": 0,
      "curveFrom": "{0.98124999999999996, 0.4566111111111108}",
      "curveMode": 4,
      "curveTo": "{0.99309999999999832, 0.46716666666666623}",
      "hasCurveFrom": false,
      "hasCurveTo": true,
      "point": "{0.98124999999999996, 0.4566111111111108}"
    }
  ],
  "resizingConstraint": 63,
  "resizingType": 0,
  "rotation": 0,
  "shouldBreakMaskChain": false,
  "style": {
    "_class": "style",
    "do_objectID": "9266C982-5974-4FAB-A764-B9468B38AF15",
    "endMarkerType": 0,
    "fills": [
      {
        "_class": "fill",
        "color": {
          "_class": "color",
          "alpha": 1,
          "blue": 0.125,
          "green": 0.122,
          "red": 0.137
        },
        "fillType": 0,
        "isEnabled": true,
        "noiseIndex": 0,
        "noiseIntensity": 0,
        "patternFillType": 1,
        "patternTileScale": 1
      }
    ],
    "miterLimit": 10,
    "startMarkerType": 0,
    "windingRule": 1
  }
}