{
  "_class": "text",
  "attributedString": {
    "_class": "attributedString",
    "attributes": [
      {
        "_class": "stringAttribute",
        "attributes": {
          "MSAttributedStringColorAttribute": {
            "_class": "color",
            "alpha": 1,
            "blue": 0.8235294117647058,
            "green": 0.5137254901960786,
            "red": 0.3137254901960784
          },
          "MSAttributedStringFontAttribute": {
            "_class": "fontDescriptor",
            "attributes": {
              "name": "Inter-Regular",
              "size": 18
            }
          },
          "kerning": 0,
          "paragraphStyle": {
            "_class": "paragraphStyle",
            "alignment": 1,
            "allowsDefaultTighteningForTruncation": 0,
            "maximumLineHeight": 28,
            "minimumLineHeight": 28
          },
          "strikethroughStyle": 0,
          "textStyleVerticalAlignmentKey": 0,
          "underlineStyle": 0
        },
        "length": 2,
        "location": 0
      }
    ],
    "string": "h5"
  },
  "automaticallyDrawOnUnderlyingPath": false,
  "booleanOperation": -1,
  "clippingMaskMode": 0,
  "do_objectID": "FAB094E8-A513-4B08-896A-CF08E7902B38",
  "dontSynchroniseWithSymbol": false,
  "exportOptions": {
    "_class": "exportOptions",
    "exportFormats": [
    ],
    "includedLayerIds": [
    ],
    "layerOptions": 0,
    "shouldTrim": false
  },
  "frame": {
    "_class": "rect",
    "constrainProportions": false,
    "height": 28,
    "width": 22,
    "x": 816,
    "y": 463
  },
  "glyphBounds": "{{1, 7}, {20, 15}}",
  "hasClippingMask": false,
  "isFixedToViewport": false,
  "isFlippedHorizontal": false,
  "isFlippedVertical": false,
  "isLocked": false,
  "isVisible": true,
  "layerListExpandedType": 0,
  "lineSpacingBehaviour": 2,
  "name": "h5/link/right",
  "nameIsFixed": false,
  "resizingConstraint": 47,
  "resizingType": 0,
  "rotation": 0,
  "sharedStyleID": "0FB5B333-5079-42B8-954C-55C1F1415BED",
  "shouldBreakMaskChain": false,
  "style": {
    "_class": "style",
    "do_objectID": "6EC06460-E0D1-4E1A-9C71-36D5FE548455",
    "endMarkerType": 0,
    "miterLimit": 10,
    "startMarkerType": 0,
    "textStyle": {
      "_class": "textStyle",
      "encodedAttributes": {
        "MSAttributedStringColorAttribute": {
          "_class": "color",
          "alpha": 1,
          "blue": 0.8235294117647058,
          "green": 0.5137254901960786,
          "red": 0.3137254901960784
        },
        "MSAttributedStringFontAttribute": {
          "_class": "fontDescriptor",
          "attributes": {
            "name": "Inter-Regular",
            "size": 18
          }
        },
        "kerning": 0,
        "paragraphStyle": {
          "_class": "paragraphStyle",
          "alignment": 1,
          "allowsDefaultTighteningForTruncation": 0,
          "maximumLineHeight": 28,
          "minimumLineHeight": 28
        },
        "strikethroughStyle": 0,
        "textStyleVerticalAlignmentKey": 0,
        "underlineStyle": 0
      },
      "verticalAlignment": 0
    },
    "windingRule": 1
  },
  "textBehaviour": 1
}