{
  "_class": "shapeGroup",
  "booleanOperation": -1,
  "clippingMaskMode": 0,
  "do_objectID": "D91F8BE1-4C64-4738-AE80-815F32BD8D4C",
  "exportOptions": {
    "_class": "exportOptions",
    "do_objectID": "E8E3BB79-0EE3-4342-9435-CE250203A876",
    "exportFormats": [
    ],
    "includedLayerIds": [
    ],
    "layerOptions": 0,
    "shouldTrim": false
  },
  "frame": {
    "_class": "rect",
    "constrainProportions": false,
    "do_objectID": "8B9907BC-CB91-4B06-9A49-CF9669A34C30",
    "height": 22.00018174408012,
    "width": 18.0005,
    "x": 2.999749999999644,
    "y": 0.99991825591988
  },
  "groupLayout": {
    "_class": "MSImmutableFreeformGroupLayout"
  },
  "hasClickThrough": false,
  "hasClippingMask": true,
  "isFixedToViewport": false,
  "isFlippedHorizontal": false,
  "isFlippedVertical": false,
  "isLocked": false,
  "isVisible": true,
  "layerListExpandedType": 0,
  "layers": [
    {
      "class": "shapePath",
      "id": "1EA7FABE-5054-45C3-82DE-16145EBC7148"
    },
    {
      "class": "shapePath",
      "id": "3293DE0A-6E0B-4F77-A5FF-949B60F34DC6"
    },
    {
      "class": "shapePath",
      "id": "19122084-6DB9-45C3-97C7-C7A99C9E894E"
    }
  ],
  "name": "color",
  "nameIsFixed": false,
  "resizingConstraint": 63,
  "resizingType": 0,
  "rotation": 0,
  "sharedStyleID": "B0E9C828-014A-447D-AB3D-6EA556512153",
  "shouldBreakMaskChain": false,
  "style": {
    "_class": "style",
    "borders": [
      {
        "_class": "border",
        "color": {
          "_class": "color",
          "alpha": 1,
          "blue": 0.592,
          "green": 0.592,
          "red": 0.592
        },
        "fillType": 0,
        "isEnabled": false,
        "position": 1,
        "thickness": 1
      }
    ],
    "do_objectID": "9926DFB3-4DE1-4136-857C-FC39496E656A",
    "endMarkerType": 0,
    "fills": [
      {
        "_class": "fill",
        "color": {
          "_class": "color",
          "alpha": 1,
          "blue": 0.1882352941176471,
          "green": 0.1568627450980392,
          "red": 0.1490196078431373
        },
        "fillType": 0,
        "isEnabled": true,
        "noiseIndex": 0,
        "noiseIntensity": 0,
        "patternFillType": 1,
        "patternTileScale": 1
      }
    ],
    "miterLimit": 10,
    "startMarkerType": 0,
    "windingRule": 1
  },
  "windingRule": 1
}